LICENSE
furo_myst_nb_css_fixes/__init__.py
furo_myst_nb_css_fixes/furo-mystnb-fixes.css
furo_myst_nb_css_fixes-0.1.1.dist-info/WHEEL
furo_myst_nb_css_fixes-0.1.1.dist-info/METADATA
furo_myst_nb_css_fixes-0.1.1.dist-info/licenses/LICENSE
furo_myst_nb_css_fixes-0.1.1.dist-info/RECORD
