Metadata-Version: 2.1
Name: furo-myst-nb-css-fixes
Version: 0.1.1
Summary: A tiny wrapper around a few lines of CSS to better support the MyST-NB Jupyter notebook outputs with the Furo Sphinx theme.
License: MIT license
Author-email: Kai Norman Clasen <k.clasen@protonmail.com>
Requires-Python: >=3.8
Requires-Dist: sphinx>=4.5
Project-URL: documentation, https://kai-tub.github.io/furo-myst-nb-css-fixes
Project-URL: homepage, https://github.com/kai-tub/furo-myst-nb-css-fixes/
Project-URL: repository, https://github.com/kai-tub/furo-myst-nb-css-fixes/
